LICENSE
MANIFEST.in
README.md
setup.cfg
setup.py
pathman2/__init__.py
pathman2/base.py
pathman2/copy.py
pathman2/exc.py
pathman2/path.py
pathman2/py.typed
pathman2/utils.py
pathman2.egg-info/PKG-INFO
pathman2.egg-info/SOURCES.txt
pathman2.egg-info/dependency_links.txt
pathman2.egg-info/requires.txt
pathman2.egg-info/top_level.txt
pathman2/_impl/__init__.py
pathman2/_impl/local.py
pathman2/_impl/s3.py