Metadata-Version: 2.1
Name: pathman2
Version: 0.1.0
Summary: Pathlib-style interface for local, remote, and cloud-based file systems
Home-page: UNKNOWN
Author: Zach Duey
Author-email: zachduey@gmail.com
License: MIT
Platform: UNKNOWN
Classifier: Development Status :: 3 - Alpha
Classifier: Topic :: Utilities
Provides-Extra: s3
